UncleDongPackage/__init__.py
UncleDongPackage/ohhhhhhhhh.py
UncleDongPackage-1.0.dist-info/LICENSE
UncleDongPackage-1.0.dist-info/METADATA
UncleDongPackage-1.0.dist-info/WHEEL
UncleDongPackage-1.0.dist-info/top_level.txt
UncleDongPackage-1.0.dist-info/RECORD
